{
  "frames": {
    "batFlyVertical1.png": {
      "frame": {"x":96, "y":0, "w":32, "h":32},
      "rotated": false,
      "trimmed": true,
      "spriteSourceSize": {"x":0, "y":0, "w":32, "h":32},
      "sourceSize": {"w":32, "h":32}
    },
    "batFlyVertical2.png": {
      "frame": {"x":64, "y":0, "w":32, "h":32},
      "rotated": false,
      "trimmed": true,
      "spriteSourceSize": {"x":0, "y":0, "w":32, "h":32},
      "sourceSize": {"w":32, "h":32}
    },
    "batFlyVertical3.png": {
      "frame": {"x":32, "y":0, "w":32, "h":32},
      "rotated": false,
      "trimmed": true,
      "spriteSourceSize": {"x":0, "y":0, "w":32, "h":32},
      "sourceSize": {"w":32, "h":32}
    },
    "batFlyVertical4.png": {
      "frame": {"x":64, "y":0, "w":32, "h":32},
      "rotated": false,
      "trimmed": true,
      "spriteSourceSize": {"x":0, "y":0, "w":32, "h":32},
      "sourceSize": {"w":32, "h":32}
    },
    "batFlyHorizontal1.png": {
      "frame": {"x":32, "y":32, "w":32, "h":32},
      "rotated": false,
      "trimmed": true,
      "spriteSourceSize": {"x":0, "y":0, "w":32, "h":32},
      "sourceSize": {"w":32, "h":32}
    },
    "batFlyHorizontal2.png": {
      "frame": {"x":64, "y":32, "w":32, "h":32},
      "rotated": false,
      "trimmed": true,
      "spriteSourceSize": {"x":0, "y":0, "w":32, "h":32},
      "sourceSize": {"w":32, "h":32}
    },
    "batFlyHorizontal3.png": {
      "frame": {"x":96, "y":32, "w":32, "h":32},
      "rotated": false,
      "trimmed": true,
      "spriteSourceSize": {"x":0, "y":0, "w":32, "h":32},
      "sourceSize": {"w":32, "h":32}
    },
    "batFlyHorizontal4.png": {
      "frame": {"x":64, "y":32, "w":32, "h":32},
      "rotated": false,
      "trimmed": true,
      "spriteSourceSize": {"x":0, "y":0, "w":32, "h":32},
      "sourceSize": {"w":32, "h":32}
    }
  },
  "meta": {
    "image": "bat_group.png",
    "format": "RGBA8888",
    "size": {"w":128, "h":128},
    "scale": "1"
  }
}